<?xml version="1.0" encoding="UTF-8"?>
<objects serializationModel="Studio.02.02.00">
	<object class="AudioFile" id="{247186e5-37cc-445c-8dbd-e4b3a18c22f0}">
		<property name="assetPath">
			<value>Ambience/People Talking/voices/GameVoices/randomVoiceA7.wav</value>
		</property>
		<property name="frequencyInKHz">
			<value>48</value>
		</property>
		<property name="channelCount">
			<value>1</value>
		</property>
		<property name="length">
			<value>3.1612499999999999</value>
		</property>
		<relationship name="masterAssetFolder">
			<destination>{df812fd1-ac55-4b51-92a9-9c427ace5e20}</destination>
		</relationship>
	</object>
</objects>
