<?xml version="1.0" encoding="UTF-8"?>
<objects serializationModel="Studio.02.02.00">
	<object class="AudioFile" id="{54d41088-c893-4be4-8a91-692123b62442}">
		<property name="assetPath">
			<value>Ambience/People Talking/voices/GameVoices/SE_PROG_SYSV_030_000000A5.wav</value>
		</property>
		<property name="frequencyInKHz">
			<value>48</value>
		</property>
		<property name="channelCount">
			<value>1</value>
		</property>
		<property name="length">
			<value>3.4481250000000001</value>
		</property>
		<relationship name="masterAssetFolder">
			<destination>{df812fd1-ac55-4b51-92a9-9c427ace5e20}</destination>
		</relationship>
	</object>
</objects>
